handy_dandy/__init__.py
handy_dandy-0.1.3.dist-info/WHEEL
handy_dandy-0.1.3.dist-info/METADATA
handy_dandy-0.1.3.dist-info/RECORD
