Metadata-Version: 2.1
Name: handy-dandy
Version: 0.1.3
Summary: A few handy tools for your python program!
License: MIT
Author: Isaiah Day
Author-email: dont@stalk.me
Requires-Python: >=3.8,<4.0
Classifier: License :: OSI Approved :: MIT License
Classifier: Programming Language :: Python :: 3
Classifier: Programming Language :: Python :: 3.8
Classifier: Programming Language :: Python :: 3.9
Requires-Dist: pyfiglet (>=0.8.post1,<0.9)
